redsem/__init__.py
redsem/api.py
redsem-0.0.4.dist-info/LICENSE
redsem-0.0.4.dist-info/METADATA
redsem-0.0.4.dist-info/WHEEL
redsem-0.0.4.dist-info/top_level.txt
redsem-0.0.4.dist-info/RECORD
