Metadata-Version: 2.1
Name: redsem
Version: 0.0.4
Summary: Convertir datos tabulares en redes semánticas
Home-page: https://git.c3.unam.mx/alejandro.prieto/redsem
Author: Mauricio Alejandro Prieto Palacios
Author-email: "Alejandro Palacios" <alejandro.prieto@c3.unam.mx>
License: MIT
Classifier: License :: OSI Approved :: MIT License
License-File: LICENSE
Requires-Dist: pandas
Requires-Dist: networkx
